selective_json_parser-0.0.8.dist-info/licenses/LICENSE
selectivejsonparser/__init__.py
selectivejsonparser/parser/__init__.py
selectivejsonparser/parser/parser.py
selectivejsonparser/pattern/__init__.py
selectivejsonparser/pattern/element.py
selectivejsonparser/pattern/pattern.py
selectivejsonparser/pattern/pattern_parser.py
selective_json_parser-0.0.8.dist-info/METADATA
selective_json_parser-0.0.8.dist-info/WHEEL
selective_json_parser-0.0.8.dist-info/top_level.txt
selective_json_parser-0.0.8.dist-info/RECORD
