Metadata-Version: 2.4
Name: selective-json-parser
Version: 0.0.8
Summary: A JSON parser that only parses the parts you need.
Author: Niclas Kjäll-Ohlsson
License-Expression: MIT
Project-URL: Homepage, https://github.com/niclasko/SelectiveJSONParser
Project-URL: Repository, https://github.com/niclasko/SelectiveJSONParser
Project-URL: Issues, https://github.com/niclasko/SelectiveJSONParser/issues
Keywords: json,parser,selective,data
Classifier: Programming Language :: Python :: 3
Classifier: Operating System :: OS Independent
Requires-Python: >=3.10
License-File: LICENSE
Requires-Dist: twine
Provides-Extra: dev
Requires-Dist: pytest>=7.0.0; extra == "dev"
Requires-Dist: pytest-cov>=4.0.0; extra == "dev"
Requires-Dist: black>=23.0.0; extra == "dev"
Requires-Dist: flake8>=6.0.0; extra == "dev"
Requires-Dist: mypy>=1.0.0; extra == "dev"
Requires-Dist: pre-commit; extra == "dev"
Dynamic: license-file
